track_api_error/__init__.py
track_api_error-1.0.0.dist-info/LICENCE.txt
track_api_error-1.0.0.dist-info/METADATA
track_api_error-1.0.0.dist-info/WHEEL
track_api_error-1.0.0.dist-info/top_level.txt
track_api_error-1.0.0.dist-info/RECORD
